__init__.py
ai.py
main.py
ui.py
the_antivirus_dg-0.2.0.dist-info/licenses/LICENSE
the_antivirus_dg-0.2.0.dist-info/METADATA
the_antivirus_dg-0.2.0.dist-info/WHEEL
the_antivirus_dg-0.2.0.dist-info/entry_points.txt
the_antivirus_dg-0.2.0.dist-info/top_level.txt
the_antivirus_dg-0.2.0.dist-info/RECORD
