Metadata-Version: 2.4
Name: the_antivirus_dg
Version: 0.2.0
Summary: Antivirus software with DDoS prevention and firewall
Author-email: Daniel Grosso <danielka17.grosso@gmail.com>, Almog <almogoxt@gmail.com>
License-Expression: MIT
Project-URL: Documentation, https://github.com/The-Antivirus/The_Antivirus#readme
Project-URL: Source, https://github.com/The-Antivirus/The_Antivirus
Project-URL: Tracker, https://github.com/The-Antivirus/The_Antivirus/issues
Requires-Python: >=3.6
License-File: LICENSE
Requires-Dist: psutil>=5.9.0
Requires-Dist: PyQt6
Requires-Dist: cryptography
Requires-Dist: requests
Requires-Dist: pillow
Requires-Dist: scapy
Requires-Dist: colorama
Requires-Dist: loguru
Requires-Dist: SpeechRecognition
Requires-Dist: googletrans==4.0.0rc1
Requires-Dist: google-generativeai
Provides-Extra: dev
Requires-Dist: pytest>=6.0; extra == "dev"
Requires-Dist: pytest-cov>=2.0; extra == "dev"
Requires-Dist: flake8>=3.9; extra == "dev"
Requires-Dist: black>=22.0; extra == "dev"
Requires-Dist: isort>=5.0; extra == "dev"
Requires-Dist: mypy>=0.910; extra == "dev"
Requires-Dist: twine>=4.0; extra == "dev"
Requires-Dist: sphinx>=4.0; extra == "dev"
Dynamic: license-file
